LICENSE.txt
MANIFEST.in
README.md
setup.py
limitloop/__init__.py
limitloop/limitloop.py
limitloop.egg-info/PKG-INFO
limitloop.egg-info/SOURCES.txt
limitloop.egg-info/dependency_links.txt
limitloop.egg-info/top_level.txt