Metadata-Version: 2.1
Name: limitloop
Version: 0.2
Summary: Limitloop is a lightweight python module for running loops that depend on precise timing.
Home-page: https://github.com/senox13/limitloop
Author: Alex Medeiros
Author-email: senox13@gmail.com
License: GPLv3
Classifier: Development Status :: 4 - Beta
Classifier: Intended Audience :: Developers
Classifier: License :: OSI Approved :: GNU General Public License v3 (GPLv3)
Classifier: Programming Language :: Python
License-File: LICENSE.txt
